rss_news_reader/__init__.py
rss_news_reader/__main__.py
rss_news_reader/rss_reader.py
rss_news_reader/argument_parser/__init__.py
rss_news_reader/argument_parser/_argparser.py
rss_news_reader/config/__init__.py
rss_news_reader/config/_config.py
rss_news_reader/converter/__init__.py
rss_news_reader/converter/_converter.py
rss_news_reader/converter/html_template.jinja2
rss_news_reader/converter/xhtml_template.jinja2
rss_news_reader/converter/fonts/DejaVuSans-Bold.ttf
rss_news_reader/converter/fonts/DejaVuSans.ttf
rss_news_reader/printer/__init__.py
rss_news_reader/printer/_printer.py
rss_news_reader/reader/__init__.py
rss_news_reader/reader/_caching.py
rss_news_reader/reader/_reader.py
rss_news_reader/rss_builder/__init__.py
rss_news_reader/rss_builder/_builder.py
rss_news_reader/rss_builder/_rss_models.py
rss_news_reader/rss_builder/_url_resolver.py
rss_news_reader/xml_parser/__init__.py
rss_news_reader/xml_parser/_parser.py
rss_news_reader/xml_parser/_parser_models.py
rss_news_reader/xml_parser/_tokenizer.py
tests/__init__.py
tests/test_builder.py
tests/test_caching.py
tests/test_parser.py
rss_news_reader-3.2.5.dist-info/LICENSE.txt
rss_news_reader-3.2.5.dist-info/METADATA
rss_news_reader-3.2.5.dist-info/WHEEL
rss_news_reader-3.2.5.dist-info/entry_points.txt
rss_news_reader-3.2.5.dist-info/top_level.txt
rss_news_reader-3.2.5.dist-info/RECORD
