Metadata-Version: 2.1
Name: rss-news-reader
Version: 3.2.5
Summary: Pure Python command-line RSS reader
Home-page: https://github.com/doppelmarker/Homework
Author: doppelmarker
Author-email: doppelmarker@gmail.com
License: MIT
Platform: UNKNOWN
Classifier: Programming Language :: Python :: 3.9
Requires-Python: >=3.9
License-File: LICENSE.txt
Requires-Dist: requests (~=2.26.0)
Requires-Dist: pydantic (~=1.8.2)
Requires-Dist: Jinja2 (~=3.0.2)
Requires-Dist: xhtml2pdf (~=0.2.5)
Requires-Dist: EbookLib (~=0.17.1)
Requires-Dist: colorama (~=0.4.4)
Provides-Extra: aiohttp
Requires-Dist: aiohttp ; extra == 'aiohttp'
